README.md
setup.py
qcloud_sms/__init__.py
qcloud_sms/sender.py
qcloud_sms/tools.py
qcloudsms.egg-info/PKG-INFO
qcloudsms.egg-info/SOURCES.txt
qcloudsms.egg-info/dependency_links.txt
qcloudsms.egg-info/requires.txt
qcloudsms.egg-info/top_level.txt