Metadata-Version: 2.1
Name: qcloudsms
Version: 0.1
Summary: Qcloud(Tecent Cloud) Python3 SMS SDK
Home-page: https://github.com/wyh/qcloudsms
Author: SamuelWu
Author-email: samuel.yh.wu@gmail.com
License: UNKNOWN
Platform: UNKNOWN
Classifier: Programming Language :: Python :: 3
Classifier: License :: OSI Approved :: MIT License
Classifier: Operating System :: OS Independent
Requires-Python: >=3.6
